koliba.cpython-35m-arm-linux-gnueabihf.so
koliba-0.0.1.dist-info/METADATA
koliba-0.0.1.dist-info/WHEEL
koliba-0.0.1.dist-info/top_level.txt
koliba-0.0.1.dist-info/RECORD
