Metadata-Version: 2.1
Name: koliba
Version: 0.0.1
Summary: A Python port of the koliba library
Home-page: https://github.com/Pantarheon/koliba
Author: G. Adam Stanislav
License: UNKNOWN
Platform: UNKNOWN
Classifier: Programming Language :: Python :: 3
Classifier: License :: OSI Approved :: BSD License
Classifier: Operating System :: OS Independent
